wordhelpers/__init__.py
wordhelpers/pydantic_models.py
wordhelpers-0.1.4.dist-info/METADATA
wordhelpers-0.1.4.dist-info/WHEEL
wordhelpers-0.1.4.dist-info/RECORD
