Metadata-Version: 2.4
Name: wordhelpers
Version: 0.1.4
Summary: Helpers for working with python-docx
Author: AJ Cruz
Author-email: 15045766-a-cruz@users.noreply.gitlab.com
Requires-Python: >=3.11
Classifier: Programming Language :: Python :: 3
Classifier: Programming Language :: Python :: 3.11
Classifier: Programming Language :: Python :: 3.12
Classifier: Programming Language :: Python :: 3.13
Classifier: Programming Language :: Python :: 3.14
Requires-Dist: pydantic (>=2.12.5,<3.0.0)
Requires-Dist: python-docx (>=1.2.0,<2.0.0)
